mac_unit.v
//
module mac_unit (
    input clk,
    input rst,
    input [7:0] activation_in,
    input [7:0] weight_in,
    output reg [7:0] activation_out,
    output reg [7:0] weight_out,
    input signed [23:0] partial_sum_in,
    output reg signed [23:0] partial_sum_out
);

always @(posedge clk ) begin
    if (rst) begin
        activation_out <= 0;
        weight_out <= 0;
        partial_sum_out <= 0;
    end else begin
        activation_out <= activation_in;           // Pass activation to next PE
        weight_out <= weight_in;                   // Pass weight to next PE
        partial_sum_out <= partial_sum_in + $signed(activation_in) * $signed(weight_in);  // MAC operation
    end
end

endmodule
// mac_unit.v - Multiply-Accumulate Unit for MAC Array

mac_unit_tb.v
`timescale 1ns/1ps
`include "mac_unit.v"
module mac_unit_tb;

    reg clk;
    reg rst;
    reg [7:0] activation_in;
    reg [7:0] weight_in;
    reg signed [23:0] partial_sum_in;

    wire [7:0] activation_out;
    wire [7:0] weight_out;
    wire signed [23:0] partial_sum_out;

    // Instantiate the MAC unit
    mac_unit uut (
        .clk(clk),
        .rst(rst),
        .activation_in(activation_in),
        .weight_in(weight_in),
        .activation_out(activation_out),
        .weight_out(weight_out),
        .partial_sum_in(partial_sum_in),
        .partial_sum_out(partial_sum_out)
    );

    // Clock generator
    always #5 clk = ~clk; // 100 MHz

    initial begin
        $dumpfile("mac_unit_tb.vcd");  // For waveform view
        $dumpvars(0, mac_unit_tb);

        // Init
        clk = 0;
        rst = 1;
        activation_in = 0;
        weight_in = 0;
        partial_sum_in = 0;

        // Hold reset for a bit
        #10;
        rst = 0;

        // Test case 1
        activation_in = 8'd3;
        weight_in = 8'd4;
        partial_sum_in = 24'd0;
        #10;

        // Test case 2
        activation_in = 8'd2;
        weight_in = -8'd5;  // test signed multiply
        partial_sum_in = partial_sum_out; // feed back
        #10;

        // Test case 3
        activation_in = -8'd7;
        weight_in = 8'd6;
        partial_sum_in = partial_sum_out;
        #10;

        $finish;
    end
endmodule

mac_unit_tb.vcd
$date
	Sat Aug  9 21:54:43 2025
$end
$version
	Icarus Verilog
$end
$timescale
	1ps
$end
$scope module mac_unit_tb $end
$var wire 8 ! weight_out [7:0] $end
$var wire 24 " partial_sum_out [23:0] $end
$var wire 8 # activation_out [7:0] $end
$var reg 8 $ activation_in [7:0] $end
$var reg 1 % clk $end
$var reg 24 & partial_sum_in [23:0] $end
$var reg 1 ' rst $end
$var reg 8 ( weight_in [7:0] $end
$scope module uut $end
$var wire 8 ) activation_in [7:0] $end
$var wire 1 % clk $end
$var wire 24 * partial_sum_in [23:0] $end
$var wire 1 ' rst $end
$var wire 8 + weight_in [7:0] $end
$var reg 8 , activation_out [7:0] $end
$var reg 24 - partial_sum_out [23:0] $end
$var reg 8 . weight_out [7:0] $end
$upscope $end
$upscope $end
$enddefinitions $end
#0
$dumpvars
bx .
bx -
bx ,
b0 +
b0 *
b0 )
b0 (
1'
b0 &
0%
b0 $
bx #
bx "
bx !
$end
#5000
b0 "
b0 -
b0 !
b0 .
b0 #
b0 ,
1%
#10000
0%
b100 (
b100 +
b11 $
b11 )
0'
#15000
b1100 "
b1100 -
b100 !
b100 .
b11 #
b11 ,
1%
#20000
0%
b1100 &
b1100 *
b11111011 (
b11111011 +
b10 $
b10 )
#25000
b10 "
b10 -
b11111011 !
b11111011 .
b10 #
b10 ,
1%
#30000
0%
b10 &
b10 *
b110 (
b110 +
b11111001 $
b11111001 )
#35000
b111111111111111111011000 "
b111111111111111111011000 -
b110 !
b110 .
b11111001 #
b11111001 ,
1%
