mac_unit.v
// author: K M Skanda
// email: kmskanda29@gmail.com
// mac_unit_lp_adv.v
// Low-power MAC with hierarchical gating, sparsity skip, and operand isolation.
// - activation_in, weight_in are signed 8-bit (quantized).
// - partial_sum is signed 24-bit (accum width).
// - local_en = en & row_en & col_en (hierarchical enable).

module mac_unit #(
    parameter A_W = 8,
    parameter W_W = 8,
    parameter PSUM_W = 24
) (
    input  wire                        clk,
    input  wire                        rst,
    // Enables
    input  wire                        en,       // per-PE enable (from scheduler / controller)
    input  wire                        row_en,   // row-level enable (hierarchical)
    input  wire                        col_en,   // column-level enable (hierarchical)
    // Data in/out (systolic dataflow)
    input  wire signed [A_W-1:0]       activation_in,
    input  wire signed [W_W-1:0]       weight_in,
    output reg  signed [A_W-1:0]       activation_out,
    output reg  signed [W_W-1:0]       weight_out,
    // Partial sum chaining
    input  wire signed [PSUM_W-1:0]    partial_sum_in,
    output reg  signed [PSUM_W-1:0]    partial_sum_out
);

    // local enable (hierarchical)
    wire local_en;
    assign local_en = en & row_en & col_en;

    // operand registers (capture operands only when local_en)
    reg signed [A_W-1:0] activation_reg;
    reg signed [W_W-1:0] weight_reg;

    // zero detection for sparsity skipping
    wire activation_is_zero = (activation_reg == {A_W{1'b0}});
    wire weight_is_zero     = (weight_reg     == {W_W{1'b0}});
    wire skip_mac           = activation_is_zero | weight_is_zero;

    // operand isolation for multiplier inputs
    // When not enabled, feed zeros to multiplier to keep the datapath quiet.
    wire signed [A_W-1:0] mult_a = local_en ? activation_reg : {A_W{1'b0}};
    wire signed [W_W-1:0] mult_b = local_en ? weight_reg     : {W_W{1'b0}};

    // multiplier product width: extend to PSUM_W to match accumulation
    wire signed [PSUM_W-1:0] mult_prod;
    // sign-extend multiplicands to PSUM_W, then multiply (synthesizable)
    wire signed [PSUM_W-1:0] mult_a_ext = {{(PSUM_W-A_W){activation_reg[A_W-1]}}, activation_reg};
    wire signed [PSUM_W-1:0] mult_b_ext = {{(PSUM_W-W_W){weight_reg[W_W-1]}},     weight_reg};

    assign mult_prod = mult_a_ext * mult_b_ext;

    // We will compute next_psum depending on skip and local_en
    wire signed [PSUM_W-1:0] next_psum;
    assign next_psum = (local_en && !skip_mac) ? (partial_sum_in + mult_prod) :
                       (local_en && skip_mac)  ? partial_sum_in : // no change if skip but enabled
                       partial_sum_out; // hold when not enabled

    // Sequential logic
    always @(posedge clk) begin
        if (rst) begin
            activation_reg  <= {A_W{1'b0}};
            weight_reg      <= {W_W{1'b0}};
            activation_out  <= {A_W{1'b0}};
            weight_out      <= {W_W{1'b0}};
            partial_sum_out <= {PSUM_W{1'b0}};
        end else begin
            // Capture inputs into registers only when local_en asserted.
            // This is operand gating: registers don't toggle when disabled.
            if (local_en) begin
                activation_reg <= activation_in;
                weight_reg     <= weight_in;
            end else begin
                activation_reg <= activation_reg; // hold
                weight_reg     <= weight_reg;     // hold
            end

            // Pass stream to next PE irrespective of local_en OR only when desired?
            // We choose to pass activation/weight_out as the incoming values so downstream PEs receive them.
            // If you want to prevent upstream toggles, you can choose to hold output when !local_en.
            activation_out <= activation_in;
            weight_out     <= weight_in;

            // Update partial sum:
            // - If local_en && not skip => accumulate product
            // - If local_en && skip => keep partial_sum_in (no operation)
            // - If !local_en => hold existing partial_sum_out (no update)
            if (local_en) begin
                if (!skip_mac) partial_sum_out <= partial_sum_in + mult_prod;
                else            partial_sum_out <= partial_sum_in; // skip multiply when operand zero
            end else begin
                partial_sum_out <= partial_sum_out; // hold
            end
        end
    end

endmodule

mac_unit_tb.v
`timescale 1ns/1ps
`include "mac_unit.v"  // or change to "mac_unit_lp_adv.v"

module mac_unit_tb;
    reg clk, rst;
    reg en, row_en, col_en;
    reg signed [7:0] activation_in, weight_in;
    reg signed [23:0] partial_sum_in;
    wire signed [7:0] activation_out, weight_out;
    wire signed [23:0] partial_sum_out;

    // Instantiate DUT
    mac_unit dut (
        .clk(clk), .rst(rst),
        .en(en), .row_en(row_en), .col_en(col_en),
        .activation_in(activation_in),
        .weight_in(weight_in),
        .activation_out(activation_out),
        .weight_out(weight_out),
        .partial_sum_in(partial_sum_in),
        .partial_sum_out(partial_sum_out)
    );

    // Clock generation
    always #5 clk = ~clk;

    initial begin
        $dumpfile("mac_unit_tb.vcd");
        $dumpvars(0, mac_unit_tb); // match testbench name

        clk = 0; rst = 1;
        en = 1; row_en = 0; col_en = 0;
        activation_in = 0; weight_in = 0; partial_sum_in = 0;
        
        // Reset phase
        #20 rst = 0;

        // Basic MAC
        en = 1; row_en = 1; col_en = 1;
        activation_in = 8'sd3; weight_in = 8'sd4; partial_sum_in = 24'sd10;
        #10;
        $display("Test1: %0d", partial_sum_out); // Expect 22

        // Sparsity skip (activation=0)
        activation_in = 8'sd0; weight_in = 8'sd5; partial_sum_in = 24'sd50;
        #10;
        $display("Test2: %0d", partial_sum_out); // Expect 50

        // Disable PE
        en = 0; activation_in = 8'sd2; weight_in = 8'sd3; partial_sum_in = 24'sd100;
        #10;
        $display("Test3: %0d", partial_sum_out); // Expect unchanged

        $finish;
    end
endmodule

mac_unit_tb.vcd
$date
	Mon Aug 11 16:39:57 2025
$end
$version
	Icarus Verilog
$end
$timescale
	1ps
$end
$scope module mac_unit_tb $end
$var wire 8 ! weight_out [7:0] $end
$var wire 24 " partial_sum_out [23:0] $end
$var wire 8 # activation_out [7:0] $end
$var reg 8 $ activation_in [7:0] $end
$var reg 1 % clk $end
$var reg 1 & col_en $end
$var reg 1 ' en $end
$var reg 24 ( partial_sum_in [23:0] $end
$var reg 1 ) row_en $end
$var reg 1 * rst $end
$var reg 8 + weight_in [7:0] $end
$scope module dut $end
$var wire 8 , activation_in [7:0] $end
$var wire 1 % clk $end
$var wire 1 & col_en $end
$var wire 1 ' en $end
$var wire 1 - local_en $end
$var wire 24 . partial_sum_in [23:0] $end
$var wire 1 ) row_en $end
$var wire 1 * rst $end
$var wire 1 / skip_mac $end
$var wire 8 0 weight_in [7:0] $end
$var wire 1 1 weight_is_zero $end
$var wire 24 2 next_psum [23:0] $end
$var wire 24 3 mult_prod [23:0] $end
$var wire 24 4 mult_b_ext [23:0] $end
$var wire 8 5 mult_b [7:0] $end
$var wire 24 6 mult_a_ext [23:0] $end
$var wire 8 7 mult_a [7:0] $end
$var wire 1 8 activation_is_zero $end
$var reg 8 9 activation_out [7:0] $end
$var reg 8 : activation_reg [7:0] $end
$var reg 24 ; partial_sum_out [23:0] $end
$var reg 8 < weight_out [7:0] $end
$var reg 8 = weight_reg [7:0] $end
$upscope $end
$upscope $end
$enddefinitions $end
#0
$dumpvars
bx =
bx <
bx ;
bx :
bx 9
x8
b0 7
bx 6
b0 5
bx 4
bx 3
bx 2
x1
b0 0
x/
b0 .
0-
b0 ,
b0 +
1*
0)
b0 (
1'
0&
0%
b0 $
bx #
bx "
bx !
$end
#5000
b0 2
b0 3
1/
b0 "
b0 ;
b0 !
b0 <
b0 #
b0 9
11
b0 4
b0 =
18
b0 6
b0 :
1%
#10000
0%
#15000
1%
#20000
b1010 2
1-
0%
b1010 (
b1010 .
b100 +
b100 0
b11 $
b11 ,
1&
1)
0*
#25000
b10110 2
b100 5
0/
b11 7
b1010 "
b1010 ;
b100 !
b100 <
b11 #
b11 9
01
b1100 3
b100 4
b100 =
08
b11 6
b11 :
1%
#30000
b111110 2
0%
b110010 (
b110010 .
b101 +
b101 0
b0 $
b0 ,
#35000
b101 5
1/
b0 7
b110010 2
b111110 "
b111110 ;
b101 !
b101 <
b0 #
b0 9
b101 4
b101 =
18
b0 3
b0 6
b0 :
1%
#40000
b0 5
b111110 2
0-
0%
b1100100 (
b1100100 .
b11 +
b11 0
b10 $
b10 ,
0'
#45000
b11 !
b11 <
b10 #
b10 9
1%
